OpeIdEcpModule/__init__.py
OpeIdEcpModule/ecp_xslt_flagument.py
OpeIdEcpModule/handler_ecp_module.py
OpeIdEcpModule/entities/__init__.py
OpeIdEcpModule/entities/ecp_session_info.py
OpeIdEcpModule/services/__init__.py
OpeIdEcpModule/services/ecp_session_service.py
OpeIdEcpModule-1.0.5.dist-info/METADATA
OpeIdEcpModule-1.0.5.dist-info/WHEEL
OpeIdEcpModule-1.0.5.dist-info/top_level.txt
OpeIdEcpModule-1.0.5.dist-info/RECORD
